npdep_client/__init__.py
npdep_client/__main__.py
npdep_client/args/Args.py
npdep_client/args/__init__.py
npdep_client/output/Output.py
npdep_client/output/__init__.py
npdep_client/registration/Registration.py
npdep_client/registration/__init__.py
npdep_client/util/Util.py
npdep_client/util/__init__.py
npdep_client-0.1.0.dist-info/METADATA
npdep_client-0.1.0.dist-info/WHEEL
npdep_client-0.1.0.dist-info/entry_points.txt
npdep_client-0.1.0.dist-info/top_level.txt
npdep_client-0.1.0.dist-info/RECORD
