Metadata-Version: 2.1
Name: npdep_client
Version: 0.1.0
Summary: Network Protocol Data Exfiltration Project Client - A modular approach for data exfiltration
Home-page: https://github.com/npdep/npdep-client
Author: npdep
Classifier: Operating System :: OS Independent 
Classifier: Programming Language :: Python :: 3 
Requires-Dist: npdep-common
